setup.cfg
setup.py
demands/__init__.py
demands/pagination.py
demands.egg-info/PKG-INFO
demands.egg-info/SOURCES.txt
demands.egg-info/dependency_links.txt
demands.egg-info/requires.txt
demands.egg-info/top_level.txt